queryrunner/__init__.py
queryrunner/__main__.py
queryrunner/cli.py
queryrunner/query.py
queryrunner/version.py
queryrunner-0.1.0.dist-info/entry_points.txt
queryrunner-0.1.0.dist-info/LICENSE
queryrunner-0.1.0.dist-info/WHEEL
queryrunner-0.1.0.dist-info/METADATA
queryrunner-0.1.0.dist-info/RECORD
